tensoul/__init__.py
tensoul/cfg.json
tensoul/cfg.py
tensoul/constants.py
tensoul/downloader.py
tensoul/model.py
tensoul/parser.py
tensoul/utils.py
tensoul-0.1.8.dist-info/METADATA
tensoul-0.1.8.dist-info/WHEEL
tensoul-0.1.8.dist-info/RECORD
